opentelemetry/exporter/otlp/version.py
opentelemetry_exporter_otlp-1.12.0.dist-info/LICENSE
opentelemetry_exporter_otlp-1.12.0.dist-info/METADATA
opentelemetry_exporter_otlp-1.12.0.dist-info/WHEEL
opentelemetry_exporter_otlp-1.12.0.dist-info/entry_points.txt
opentelemetry_exporter_otlp-1.12.0.dist-info/top_level.txt
opentelemetry_exporter_otlp-1.12.0.dist-info/RECORD
