Metadata-Version: 2.1
Name: opentelemetry-exporter-otlp
Version: 1.12.0
Summary: OpenTelemetry Collector Exporters
Home-page: https://github.com/open-telemetry/opentelemetry-python/tree/main/exporter/opentelemetry-exporter-otlp
Author: OpenTelemetry Authors
Author-email: cncf-opentelemetry-contributors@lists.cncf.io
License: Apache-2.0
Platform: any
Classifier: Development Status :: 5 - Production/Stable
Classifier: Intended Audience :: Developers
Classifier: License :: OSI Approved :: Apache Software License
Classifier: Programming Language :: Python
Classifier: Programming Language :: Python :: 3
Classifier: Programming Language :: Python :: 3.6
Classifier: Programming Language :: Python :: 3.7
Classifier: Programming Language :: Python :: 3.8
Classifier: Programming Language :: Python :: 3.9
Classifier: Programming Language :: Python :: 3.10
Classifier: Typing :: Typed
Requires-Python: >=3.6
License-File: LICENSE
Requires-Dist: opentelemetry-exporter-otlp-proto-grpc (==1.12.0)
Requires-Dist: opentelemetry-exporter-otlp-proto-http (==1.12.0)
